isomorphic_fetch-0.0.0.0.dev4.dist-info/METADATA
isomorphic_fetch-0.0.0.0.dev4.dist-info/WHEEL
isomorphic_fetch-0.0.0.0.dev4.dist-info/entry_points.txt
isomorphic_fetch/__init__.py
isomorphic_fetch/cli.py
isomorphic_fetch/impl/common.py
isomorphic_fetch/impl/non_stream/__init__.py
isomorphic_fetch/impl/non_stream/common.py
isomorphic_fetch/impl/non_stream/non_pyodide.py
isomorphic_fetch/impl/non_stream/pyodide.py
isomorphic_fetch-0.0.0.0.dev4.dist-info/RECORD
