Metadata-Version: 2.1
Name: isomorphic-fetch
Version: 0.0.0.0.dev4
Summary: Simple fetch API for both pyodide and non-pyodide environments
Author-Email: Muspi Merol <me@promplate.dev>
Requires-Python: >=3.10
Requires-Dist: niquests==3.*; sys_platform != "emscripten"
